sergio_rs-0.2.0.dist-info/METADATA
sergio_rs-0.2.0.dist-info/WHEEL
sergio_rs-0.2.0.dist-info/license_files/LICENSE
sergio_rs/py.typed
sergio_rs/__init__.py
sergio_rs/sergio_rs.pyi
sergio_rs/sergio_rs.pypy310-pp73-x86-linux-gnu.so
sergio_rs-0.2.0.dist-info/RECORD
