Metadata-Version: 2.3
Name: sergio_rs
Version: 0.2.0
Classifier: Programming Language :: Rust
Classifier: Programming Language :: Python :: Implementation :: CPython
Classifier: Programming Language :: Python :: Implementation :: PyPy
Classifier: Development Status :: 4 - Beta
Classifier: Intended Audience :: Science/Research
Classifier: Topic :: Scientific/Engineering :: Bio-Informatics
Classifier: Programming Language :: Rust
Requires-Dist: polars ==0.20.18
Requires-Dist: numpy ==1.26.4
License-File: LICENSE
Requires-Python: >=3.10
